sunshinesocks/__init__.py
sunshinesocks-0.1.0.dist-info/METADATA
sunshinesocks-0.1.0.dist-info/RECORD
sunshinesocks-0.1.0.dist-info/WHEEL
sunshinesocks-0.1.0.dist-info/top_level.txt
