Metadata-Version: 2.1
Name: sunshinesocks
Version: 0.1.0
Summary: A fast and modern tunnel proxy that help you.
Home-page: https://github.com/tcztzy/sunshinesocks
Author: tcztzy
Author-email: tcztzy@gmail.com
License: https://www.gnu.org/licenses/gpl-3.0.en.html
Platform: UNKNOWN
Classifier: License :: OSI Approved :: Apache Software License
Classifier: Framework :: AsyncIO
Classifier: Programming Language :: Python :: 3 :: Only
Classifier: Programming Language :: Python :: 3.5
Classifier: Programming Language :: Python :: 3.6
Classifier: Programming Language :: Python :: 3.7
Classifier: Programming Language :: Python :: Implementation :: CPython
Classifier: Programming Language :: Python :: Implementation :: PyPy
Classifier: Topic :: Internet :: Proxy Servers
Requires-Dist: uvloop; implementation_name == "cpython" and platform_system != "Windows"
